./.gitignore
./Dockerfile
./LICENSE
./PKG-INFO
./README.md
./mcp_client.py
./mcp_dummy.py
./mcp_server.py
./pyproject.toml
./uv.lock
./.github/workflows/docker-build.yml
./.github/workflows/lint.yml
./.github/workflows/publish-pypi.yml
stealth_browser_mcp-0.1.4.dist-info/METADATA
stealth_browser_mcp-0.1.4.dist-info/WHEEL
stealth_browser_mcp-0.1.4.dist-info/entry_points.txt
stealth_browser_mcp-0.1.4.dist-info/licenses/LICENSE
stealth_browser_mcp-0.1.4.dist-info/RECORD
