Metadata-Version: 2.4
Name: stealth-browser-mcp
Version: 0.1.4
Summary: A Model Context Protocol (MCP) server that provides browser automation capabilities using Playwright with stealth features
License-File: LICENSE
Requires-Python: >=3.10
Requires-Dist: fastmcp>=2.5.2
Requires-Dist: playwright>=1.52.0
Requires-Dist: tf-playwright-stealth>=1.1.2
Provides-Extra: dev
Requires-Dist: black>=22.0.0; extra == 'dev'
Requires-Dist: pytest>=7.0.0; extra == 'dev'
Requires-Dist: ruff>=0.1.0; extra == 'dev'
